integration_tests/__init__.py
integration_tests/abnormal_state.json
integration_tests/acceptance.py
integration_tests/catalog.json
integration_tests/configured_catalog.json
integration_tests/invalid_config.json
integration_tests/sample_config.json
integration_tests/sample_state.json
source_search_metrics/__init__.py
source_search_metrics/run.py
source_search_metrics/source.py
source_search_metrics/spec.json
source_search_metrics/utils.py
source_search_metrics/schemas/benchmark_rankings_s7.json
source_search_metrics/schemas/competitor_rankings_s7.json
source_search_metrics/schemas/count_domain_keyword.json
source_search_metrics/schemas/distribution_keywords_s7.json
source_search_metrics/schemas/keyword_potentials_s7.json
source_search_metrics/schemas/list_competitors.json
source_search_metrics/schemas/list_competitors_relevancy.json
source_search_metrics/schemas/list_losers_s7.json
source_search_metrics/schemas/list_market_share_s7.json
source_search_metrics/schemas/list_position_spread_historic_s7.json
source_search_metrics/schemas/list_rankings_analysis_s7.json
source_search_metrics/schemas/list_rankings_domain.json
source_search_metrics/schemas/list_rankings_historic_s7.json
source_search_metrics/schemas/list_seo_visibility_country.json
source_search_metrics/schemas/list_seo_visibility_historic_s7.json
source_search_metrics/schemas/list_serp_spread_s7.json
source_search_metrics/schemas/list_winners_s7.json
source_search_metrics/schemas/marketshare_value_s7.json
source_search_metrics/schemas/projects.json
source_search_metrics/schemas/seo_visibility_value_s7.json
source_search_metrics/schemas/serp_spread_value_s7.json
source_search_metrics/schemas/tag_potentials_s7.json
source_search_metrics/schemas/tags.json
source_search_metrics/schemas/url_rankings_s7.json
airbyte_source_search_metrics-0.1.1.dist-info/METADATA
airbyte_source_search_metrics-0.1.1.dist-info/WHEEL
airbyte_source_search_metrics-0.1.1.dist-info/entry_points.txt
airbyte_source_search_metrics-0.1.1.dist-info/top_level.txt
airbyte_source_search_metrics-0.1.1.dist-info/RECORD
